<?xml version="1.0"?>
<annotation>
    <folder>images</folder>
    <filename>M5_S01_008_p_nic002.JPG</filename>
    <path>images/M5_S01_008_p_nic002.JPG</path>
    <source>
        <database>Unknown</database>
    </source>
    <size>
        <width>5940</width>
        <height>3960</height>
        <depth>3</depth>
    </size>
    <segmented>0</segmented>
    <object>
        <name>M5_S01_008_p_nic002</name>
        <pose>Unspecified</pose>
        <truncated>0</truncated>
        <difficult>0</difficult>
        <bndbox>
            <xmin>2834.999999999998</xmin>
            <ymin>2229.9999999999986</ymin>
            <xmax>5595.000610351559</xmax>
            <ymax>3559.9999999999977</ymax>
        </bndbox>
    </object>
</annotation>