<?xml version="1.0"?>
<annotation>
    <folder>images</folder>
    <filename>m5_s03_093_x.JPG</filename>
    <path>images/m5_s03_093_x.JPG</path>
    <source>
        <database>Unknown</database>
    </source>
    <size>
        <width>6000</width>
        <height>4000</height>
        <depth>3</depth>
    </size>
    <segmented>0</segmented>
    <object>
        <name>m5_s03_093_x</name>
        <pose>Unspecified</pose>
        <truncated>0</truncated>
        <difficult>0</difficult>
        <bndbox>
            <xmin>650.0000762939444</xmin>
            <ymin>579.9999999999992</ymin>
            <xmax>5349.999999999993</xmax>
            <ymax>3419.999999999995</ymax>
        </bndbox>
    </object>
</annotation>