<?xml version="1.0"?>
<annotation>
    <folder>images</folder>
    <filename>m5_s03_037_p_nic041.JPG</filename>
    <path>images/m5_s03_037_p_nic041.JPG</path>
    <source>
        <database>Unknown</database>
    </source>
    <size>
        <width>5940</width>
        <height>3960</height>
        <depth>3</depth>
    </size>
    <segmented>0</segmented>
    <object>
        <name>m5_s03_037_p_nic041</name>
        <pose>Unspecified</pose>
        <truncated>0</truncated>
        <difficult>0</difficult>
        <bndbox>
            <xmin>720.0000762939443</xmin>
            <ymin>1679.9999999999977</ymin>
            <xmax>1920.000152587888</xmax>
            <ymax>3829.9999999999945</ymax>
        </bndbox>
    </object>
</annotation>